datasette_doublemetaphone/__init__.py
datasette_doublemetaphone-0.1.dist-info/LICENSE
datasette_doublemetaphone-0.1.dist-info/METADATA
datasette_doublemetaphone-0.1.dist-info/WHEEL
datasette_doublemetaphone-0.1.dist-info/entry_points.txt
datasette_doublemetaphone-0.1.dist-info/top_level.txt
datasette_doublemetaphone-0.1.dist-info/RECORD
