Metadata-Version: 2.1
Name: datasette-doublemetaphone
Version: 0.1
Summary: Datasette plugin adding SQL functions for Double Metaphone fuzzy text matching
Home-page: https://github.com/dracos/datasette-doublemetaphone
Author: Matthew Somerville
License: Apache License, Version 2.0
Platform: UNKNOWN
Requires-Dist: datasette
Requires-Dist: doublemetaphone
